grimoire_elk_public_inbox/__init__.py
grimoire_elk_public_inbox/_version.py
grimoire_elk_public_inbox/enriched/__init__.py
grimoire_elk_public_inbox/enriched/public_inbox.py
grimoire_elk_public_inbox/raw/__init__.py
grimoire_elk_public_inbox/raw/public_inbox.py
grimoire_elk_public_inbox/utils.py
grimoire_elk_public_inbox-0.1.8.dist-info/LICENSE
grimoire_elk_public_inbox-0.1.8.dist-info/METADATA
grimoire_elk_public_inbox-0.1.8.dist-info/WHEEL
grimoire_elk_public_inbox-0.1.8.dist-info/entry_points.txt
grimoire_elk_public_inbox-0.1.8.dist-info/RECORD
