Metadata-Version: 2.1
Name: grimoire-elk-public-inbox
Version: 0.1.8
Summary: GrimoireELK plugic for public-inbox.
Home-page: https://chaoss.github.io/grimoirelab/
License: GPL-3.0+
Keywords: development,grimoirelab
Author: GrimoireLab Developers
Requires-Python: >=3.8,<4.0
Classifier: Development Status :: 4 - Beta
Classifier: Intended Audience :: Developers
Classifier: Intended Audience :: Science/Research
Classifier: License :: OSI Approved :: GNU General Public License v3 or later (GPLv3+)
Classifier: Programming Language :: Python :: 3
Classifier: Programming Language :: Python :: 3.8
Classifier: Programming Language :: Python :: 3.9
Classifier: Programming Language :: Python :: 3.10
Classifier: Programming Language :: Python :: 3.11
Classifier: Topic :: Software Development
Requires-Dist: cachetools (==5.3.1)
Requires-Dist: charset-normalizer (==3.3.0)
Requires-Dist: cryptography (==41.0.4)
Requires-Dist: grimoire-elk (>=0.106.0)
Requires-Dist: perceval-public-inbox (>=0.1.1)
Requires-Dist: pylint (==3.0.1)
Project-URL: Bug Tracker, https://github.com/bitergia-analytics/grimoirelab-elk-public-inbox/issues
Project-URL: Repository, https://github.com/bitergia-analytics/grimoirelab-elk-public-inbox
